setup.py
My_first_pypi_upload_package/Binomialdistribution.py
My_first_pypi_upload_package/Gaussiandistribution.py
My_first_pypi_upload_package/Generaldistribution.py
My_first_pypi_upload_package/__init__.py
My_first_pypi_upload_package.egg-info/PKG-INFO
My_first_pypi_upload_package.egg-info/SOURCES.txt
My_first_pypi_upload_package.egg-info/dependency_links.txt
My_first_pypi_upload_package.egg-info/not-zip-safe
My_first_pypi_upload_package.egg-info/top_level.txt